[[{"item1":"100年","item2":"二仁溪","value1":"65.2","value2":"11.0","value3":"8.9","value4":"29.7","value5":"15.6"}],[{"item1":"100年","item2":"高屏溪","value1":"170.9","value2":"47.4","value3":"7.6","value4":"115.9","value5":"0.0"}],[{"item1":"100年","item2":"阿公店溪","value1":"29.7","value2":"7.9","value3":"3.2","value4":"8.2","value5":"10.4"}],[{"item1":"100年","item2":"鳳山溪","value1":"45.4","value2":"38.4","value3":"4.4","value4":"2.7","value5":"0.0"}],[{"item1":"101年","item2":"二仁溪","value1":"65.2","value2":"8.2","value3":"10.8","value4":"33.3","value5":"12.9"}],[{"item1":"101年","item2":"高屏溪","value1":"170.9","value2":"0.7","value3":"10.2","value4":"158.2","value5":"1.8"}],[{"item1":"101年","item2":"阿公店溪","value1":"29.7","value2":"5.0","value3":"4.6","value4":"11.0","value5":"9.1"}],[{"item1":"101年","item2":"鳳山溪","value1":"45.4","value2":"38.3","value3":"4.9","value4":"2.2","value5":"0.0"}],[{"item1":"102年","item2":"二仁溪","value1":"65.2","value2":"0.7","value3":"2.6","value4":"37.8","value5":"24.1"}],[{"item1":"102年","item2":"高屏溪","value1":"170.9","value2":"20.3","value3":"1.8","value4":"146.1","value5":"2.7"}],[{"item1":"102年","item2":"阿公店溪","value1":"29.7","value2":"9.2","value3":"1.7","value4":"10.0","value5":"8.8"}],[{"item1":"102年","item2":"鳳山溪","value1":"45.4","value2":"39.6","value3":"4.0","value4":"1.9","value5":"0.0"}],[{"item1":"103年","item2":"二仁溪","value1":"65.2","value2":"6.1","value3":"1.8","value4":"36.5","value5":"20.9"}],[{"item1":"103年","item2":"高屏溪","value1":"170.9","value2":"11.4","value3":"33.5","value4":"124.5","value5":"1.5"}],[{"item1":"103年","item2":"阿公店溪","value1":"29.7","value2":"5.6","value3":"3.3","value4":"14.7","value5":"6.1"}],[{"item1":"103年","item2":"鳳山溪","value1":"45.4","value2":"35.6","value3":"4.3","value4":"5.5","value5":"0.0"}],[{"item1":"104年","item2":"二仁溪","value1":"65.2","value2":"3.2","value3":"10.0","value4":"42.5","value5":"9.5"}],[{"item1":"104年","item2":"高屏溪","value1":"170.9","value2":"69.0","value3":"14.6","value4":"83.2","value5":"4.1"}],[{"item1":"104年","item2":"阿公店溪","value1":"29.7","value2":"7.4","value3":"7.0","value4":"12.3","value5":"3.0"}],[{"item1":"104年","item2":"鳳山溪","value1":"45.4","value2":"39.0","value3":"5.4","value4":"1.1","value5":"0.0"}],[{"item1":"105年","item2":"二仁溪","value1":"65.2","value2":"5.5","value3":"10.7","value4":"34.9","value5":"14.1"}],[{"item1":"105年","item2":"高屏溪","value1":"170.9","value2":"9.3","value3":"12.7","value4":"147.1","value5":"1.8"}],[{"item1":"105年","item2":"阿公店溪","value1":"29.7","value2":"9.0","value3":"5.6","value4":"11.8","value5":"3.3"}],[{"item1":"105年","item2":"鳳山溪","value1":"45.4","value2":"37.0","value3":"5.7","value4":"2.8","value5":"0.0"}],[{"item1":"106年","item2":"二仁溪","value1":"65.2","value2":"17.8","value3":"7.7","value4":"26.9","value5":"12.9"}],[{"item1":"106年","item2":"高屏溪","value1":"170.9","value2":"89.7","value3":"15.2","value4":"64.3","value5":"1.8"}],[{"item1":"106年","item2":"阿公店溪","value1":"29.7","value2":"14.2","value3":"3.7","value4":"8.8","value5":"3.0"}],[{"item1":"106年","item2":"鳳山溪","value1":"45.4","value2":"38.9","value3":"4.1","value4":"2.4","value5":"0.0"}],[{"item1":"107年","item2":"二仁溪","value1":"65.2","value2":"3.0","value3":"6.4","value4":"42.9","value5":"12.8"}],[{"item1":"107年","item2":"高屏溪","value1":"170.9","value2":"33.4","value3":"15.9","value4":"120.5","value5":"1.1"}],[{"item1":"107年","item2":"阿公店溪","value1":"29.7","value2":"10.5","value3":"5.3","value4":"11.7","value5":"2.2"}],[{"item1":"107年","item2":"鳳山溪","value1":"45.4","value2":"39.9","value3":"3.3","value4":"2.3","value5":"0.0"}],[{"item1":"108年","item2":"二仁溪","value1":"65.2","value2":"2.3","value3":"9.4","value4":"42.4","value5":"11.2"}],[{"item1":"108年","item2":"高屏溪","value1":"170.9","value2":"53.8","value3":"7.3","value4":"108.0","value5":"1.8"}],[{"item1":"108年","item2":"阿公店溪","value1":"29.7","value2":"6.2","value3":"7.4","value4":"11.0","value5":"5.2"}],[{"item1":"108年","item2":"鳳山溪","value1":"45.4","value2":"37.8","value3":"2.8","value4":"4.8","value5":"0.0"}],[],[],[],[]]